aiothread/__init__.py
aiothread-0.0.1.dist-info/DESCRIPTION.rst
aiothread-0.0.1.dist-info/METADATA
aiothread-0.0.1.dist-info/RECORD
aiothread-0.0.1.dist-info/WHEEL
aiothread-0.0.1.dist-info/metadata.json
aiothread-0.0.1.dist-info/top_level.txt
